CHANGELOG.md
LICENSE.txt
MANIFEST.in
README.rst
setup.cfg
setup.py
flasksaml2idp/__init__.py
flasksaml2idp/error_views.py
flasksaml2idp/processors.py
flasksaml2idp/urls.py
flasksaml2idp/util.py
flasksaml2idp/views.py
flasksaml2idp.egg-info/PKG-INFO
flasksaml2idp.egg-info/SOURCES.txt
flasksaml2idp.egg-info/dependency_links.txt
flasksaml2idp.egg-info/not-zip-safe
flasksaml2idp.egg-info/requires.txt
flasksaml2idp.egg-info/top_level.txt
flasksaml2idp/templates/flasksaml2idp/error.html
flasksaml2idp/templates/flasksaml2idp/login.html