Metadata-Version: 1.2
Name: flasksaml2idp
Version: 0.1.0
Summary: SAML 2.0 Identity Provider for Flask
Home-page: https://github.com/verenigingcampuskabel/flask-saml2idp/
Author: Yoeri Otten, Mathieu Hinderyckx
Author-email: yoeri@vck.utwente.nl, mathieu.hinderyckx@gmail.com
Maintainer: Yoeri Otten
License: Apache Software License 2.0
Keywords: flask,pysaml2,sso,saml2,federated authentication,authentication,idp
Platform: UNKNOWN
Classifier: Development Status :: 5 - Production/Stable
Classifier: Environment :: Web Environment
Classifier: Framework :: Flask
Classifier: Intended Audience :: Developers
Classifier: Intended Audience :: Information Technology
Classifier: License :: OSI Approved :: Apache Software License
Classifier: Operating System :: OS Independent
Classifier: Programming Language :: Python
Classifier: Programming Language :: Python :: 3
Classifier: Programming Language :: Python :: 3.5
Classifier: Programming Language :: Python :: 3.6
Classifier: Programming Language :: Python :: 3.7
Classifier: Programming Language :: Python :: 3.8
Classifier: Topic :: Internet :: WWW/HTTP
Classifier: Topic :: Internet :: WWW/HTTP :: WSGI
Classifier: Topic :: Security
Classifier: Topic :: Software Development :: Libraries :: Application Frameworks
Classifier: Topic :: Internet :: WWW/HTTP :: Dynamic Content
Classifier: Topic :: Software Development :: Libraries :: Python Modules
